porosdata_processor/__init__.py
porosdata_processor/__main__.py
porosdata_processor/citation_rules.py
porosdata_processor/config.py
porosdata_processor/document_numbering_rules.py
porosdata_processor/greek_latex_converter.py
porosdata_processor/patterns.py
porosdata_processor/plugin_system.py
porosdata_processor/py.typed
porosdata_processor/text_cleaner.py
porosdata_processor/unicode_norm.py
porosdata_processor/utils.py
porosdata_processor/examples/basic_usage.py
porosdata_processor/examples/test_latex_math_spaces_md_json.py
porosdata_processor/examples/test_latex_space_example.py
porosdata_processor-0.2.2.dist-info/METADATA
porosdata_processor-0.2.2.dist-info/WHEEL
porosdata_processor-0.2.2.dist-info/entry_points.txt
porosdata_processor-0.2.2.dist-info/top_level.txt
porosdata_processor-0.2.2.dist-info/RECORD
