Metadata-Version: 2.1
Name: porosdata-processor
Version: 0.2.2
Summary: Professional text cleaning tool supporting Markdown code block and LaTeX formula protection, automatic citation normalization, and Chinese-English typesetting optimization
Author-email: Kivent YE <72405514@cityu-dg.edu.cn>
Maintainer-email: Kivent YE <72405514@cityu-dg.edu.cn>
License: MIT
Keywords: text,cleaning,latex,greek,preprocessing,nlp,llm,token-optimization
Classifier: Development Status :: 3 - Alpha
Classifier: Intended Audience :: Developers
Classifier: Intended Audience :: Science/Research
Classifier: Programming Language :: Python :: 3
Classifier: Programming Language :: Python :: 3.8
Classifier: Programming Language :: Python :: 3.9
Classifier: Programming Language :: Python :: 3.10
Classifier: Programming Language :: Python :: 3.11
Classifier: Topic :: Text Processing
Classifier: Topic :: Scientific/Engineering
Classifier: Topic :: Scientific/Engineering :: Artificial Intelligence
Requires-Python: >=3.8
Provides-Extra: dev
Requires-Dist: pytest>=7.0; extra == "dev"
Requires-Dist: pytest-cov>=4.0; extra == "dev"
Requires-Dist: black>=23.0; extra == "dev"
Requires-Dist: flake8>=6.0; extra == "dev"
Requires-Dist: mypy>=1.0; extra == "dev"
Requires-Dist: chardet>=5.0; extra == "dev"
